<annotation>
	<folder>photo</folder>
	<filename>hpdji815.jpg</filename>
	<path>D:\SteamLibrary\data\photo\hpdji815.jpg</path>
	<source>
		<database>Unknown</database>
	</source>
	<size>
		<width>3840</width>
		<height>2160</height>
		<depth>3</depth>
	</size>
	<segmented>0</segmented>
	<object>
		<name>person</name>
		<pose>Unspecified</pose>
		<truncated>0</truncated>
		<difficult>0</difficult>
		<bndbox>
			<xmin>39</xmin>
			<ymin>1241</ymin>
			<xmax>92</xmax>
			<ymax>1324</ymax>
		</bndbox>
	</object>
	<object>
		<name>person</name>
		<pose>Unspecified</pose>
		<truncated>0</truncated>
		<difficult>0</difficult>
		<bndbox>
			<xmin>2269</xmin>
			<ymin>1185</ymin>
			<xmax>2306</xmax>
			<ymax>1261</ymax>
		</bndbox>
	</object>
	<object>
		<name>person</name>
		<pose>Unspecified</pose>
		<truncated>0</truncated>
		<difficult>0</difficult>
		<bndbox>
			<xmin>2438</xmin>
			<ymin>1178</ymin>
			<xmax>2474</xmax>
			<ymax>1258</ymax>
		</bndbox>
	</object>
	<object>
		<name>person</name>
		<pose>Unspecified</pose>
		<truncated>0</truncated>
		<difficult>0</difficult>
		<bndbox>
			<xmin>2101</xmin>
			<ymin>1959</ymin>
			<xmax>2161</xmax>
			<ymax>2107</ymax>
		</bndbox>
	</object>
	<object>
		<name>person</name>
		<pose>Unspecified</pose>
		<truncated>1</truncated>
		<difficult>0</difficult>
		<bndbox>
			<xmin>2182</xmin>
			<ymin>2106</ymin>
			<xmax>2258</xmax>
			<ymax>2160</ymax>
		</bndbox>
	</object>
	<object>
		<name>person</name>
		<pose>Unspecified</pose>
		<truncated>0</truncated>
		<difficult>0</difficult>
		<bndbox>
			<xmin>3555</xmin>
			<ymin>1694</ymin>
			<xmax>3585</xmax>
			<ymax>1767</ymax>
		</bndbox>
	</object>
	<object>
		<name>person</name>
		<pose>Unspecified</pose>
		<truncated>0</truncated>
		<difficult>0</difficult>
		<bndbox>
			<xmin>3065</xmin>
			<ymin>1948</ymin>
			<xmax>3132</xmax>
			<ymax>2011</ymax>
		</bndbox>
	</object>
	<object>
		<name>person</name>
		<pose>Unspecified</pose>
		<truncated>0</truncated>
		<difficult>0</difficult>
		<bndbox>
			<xmin>3093</xmin>
			<ymin>1839</ymin>
			<xmax>3161</xmax>
			<ymax>1923</ymax>
		</bndbox>
	</object>
	<object>
		<name>person</name>
		<pose>Unspecified</pose>
		<truncated>0</truncated>
		<difficult>0</difficult>
		<bndbox>
			<xmin>2907</xmin>
			<ymin>1784</ymin>
			<xmax>2955</xmax>
			<ymax>1845</ymax>
		</bndbox>
	</object>
	<object>
		<name>person</name>
		<pose>Unspecified</pose>
		<truncated>0</truncated>
		<difficult>0</difficult>
		<bndbox>
			<xmin>2918</xmin>
			<ymin>1185</ymin>
			<xmax>2953</xmax>
			<ymax>1225</ymax>
		</bndbox>
	</object>
	<object>
		<name>person</name>
		<pose>Unspecified</pose>
		<truncated>0</truncated>
		<difficult>0</difficult>
		<bndbox>
			<xmin>3502</xmin>
			<ymin>1777</ymin>
			<xmax>3542</xmax>
			<ymax>1836</ymax>
		</bndbox>
	</object>
	<object>
		<name>helmet</name>
		<pose>Unspecified</pose>
		<truncated>0</truncated>
		<difficult>0</difficult>
		<bndbox>
			<xmin>54</xmin>
			<ymin>1243</ymin>
			<xmax>69</xmax>
			<ymax>1254</ymax>
		</bndbox>
	</object>
	<object>
		<name>vest</name>
		<pose>Unspecified</pose>
		<truncated>0</truncated>
		<difficult>0</difficult>
		<bndbox>
			<xmin>49</xmin>
			<ymin>1258</ymin>
			<xmax>76</xmax>
			<ymax>1293</ymax>
		</bndbox>
	</object>
	<object>
		<name>vest</name>
		<pose>Unspecified</pose>
		<truncated>0</truncated>
		<difficult>0</difficult>
		<bndbox>
			<xmin>2275</xmin>
			<ymin>1203</ymin>
			<xmax>2298</xmax>
			<ymax>1238</ymax>
		</bndbox>
	</object>
	<object>
		<name>vest</name>
		<pose>Unspecified</pose>
		<truncated>0</truncated>
		<difficult>0</difficult>
		<bndbox>
			<xmin>2447</xmin>
			<ymin>1198</ymin>
			<xmax>2469</xmax>
			<ymax>1240</ymax>
		</bndbox>
	</object>
	<object>
		<name>helmet</name>
		<pose>Unspecified</pose>
		<truncated>0</truncated>
		<difficult>0</difficult>
		<bndbox>
			<xmin>2448</xmin>
			<ymin>1180</ymin>
			<xmax>2468</xmax>
			<ymax>1191</ymax>
		</bndbox>
	</object>
	<object>
		<name>helmet</name>
		<pose>Unspecified</pose>
		<truncated>0</truncated>
		<difficult>0</difficult>
		<bndbox>
			<xmin>2281</xmin>
			<ymin>1185</ymin>
			<xmax>2302</xmax>
			<ymax>1196</ymax>
		</bndbox>
	</object>
	<object>
		<name>vest</name>
		<pose>Unspecified</pose>
		<truncated>0</truncated>
		<difficult>0</difficult>
		<bndbox>
			<xmin>2913</xmin>
			<ymin>1782</ymin>
			<xmax>2940</xmax>
			<ymax>1809</ymax>
		</bndbox>
	</object>
	<object>
		<name>helmet</name>
		<pose>Unspecified</pose>
		<truncated>0</truncated>
		<difficult>0</difficult>
		<bndbox>
			<xmin>2944</xmin>
			<ymin>1784</ymin>
			<xmax>2957</xmax>
			<ymax>1798</ymax>
		</bndbox>
	</object>
	<object>
		<name>helmet</name>
		<pose>Unspecified</pose>
		<truncated>0</truncated>
		<difficult>0</difficult>
		<bndbox>
			<xmin>3134</xmin>
			<ymin>1842</ymin>
			<xmax>3154</xmax>
			<ymax>1858</ymax>
		</bndbox>
	</object>
	<object>
		<name>vest</name>
		<pose>Unspecified</pose>
		<truncated>0</truncated>
		<difficult>0</difficult>
		<bndbox>
			<xmin>3094</xmin>
			<ymin>1856</ymin>
			<xmax>3137</xmax>
			<ymax>1883</ymax>
		</bndbox>
	</object>
	<object>
		<name>helmet</name>
		<pose>Unspecified</pose>
		<truncated>0</truncated>
		<difficult>0</difficult>
		<bndbox>
			<xmin>3092</xmin>
			<ymin>1954</ymin>
			<xmax>3114</xmax>
			<ymax>1973</ymax>
		</bndbox>
	</object>
	<object>
		<name>vest</name>
		<pose>Unspecified</pose>
		<truncated>0</truncated>
		<difficult>0</difficult>
		<bndbox>
			<xmin>3067</xmin>
			<ymin>1961</ymin>
			<xmax>3094</xmax>
			<ymax>1988</ymax>
		</bndbox>
	</object>
	<object>
		<name>vest</name>
		<pose>Unspecified</pose>
		<truncated>0</truncated>
		<difficult>0</difficult>
		<bndbox>
			<xmin>3559</xmin>
			<ymin>1709</ymin>
			<xmax>3584</xmax>
			<ymax>1741</ymax>
		</bndbox>
	</object>
	<object>
		<name>helmet</name>
		<pose>Unspecified</pose>
		<truncated>0</truncated>
		<difficult>0</difficult>
		<bndbox>
			<xmin>3563</xmin>
			<ymin>1696</ymin>
			<xmax>3578</xmax>
			<ymax>1708</ymax>
		</bndbox>
	</object>
	<object>
		<name>vest</name>
		<pose>Unspecified</pose>
		<truncated>0</truncated>
		<difficult>0</difficult>
		<bndbox>
			<xmin>3510</xmin>
			<ymin>1798</ymin>
			<xmax>3537</xmax>
			<ymax>1829</ymax>
		</bndbox>
	</object>
	<object>
		<name>vest</name>
		<pose>Unspecified</pose>
		<truncated>0</truncated>
		<difficult>0</difficult>
		<bndbox>
			<xmin>2188</xmin>
			<ymin>2118</ymin>
			<xmax>2221</xmax>
			<ymax>2153</ymax>
		</bndbox>
	</object>
	<object>
		<name>vest</name>
		<pose>Unspecified</pose>
		<truncated>0</truncated>
		<difficult>0</difficult>
		<bndbox>
			<xmin>2114</xmin>
			<ymin>1985</ymin>
			<xmax>2129</xmax>
			<ymax>2021</ymax>
		</bndbox>
	</object>
	<object>
		<name>vest</name>
		<pose>Unspecified</pose>
		<truncated>0</truncated>
		<difficult>0</difficult>
		<bndbox>
			<xmin>2124</xmin>
			<ymin>2008</ymin>
			<xmax>2147</xmax>
			<ymax>2052</ymax>
		</bndbox>
	</object>
	<object>
		<name>helmet</name>
		<pose>Unspecified</pose>
		<truncated>0</truncated>
		<difficult>0</difficult>
		<bndbox>
			<xmin>2219</xmin>
			<ymin>2105</ymin>
			<xmax>2243</xmax>
			<ymax>2133</ymax>
		</bndbox>
	</object>
	<object>
		<name>helmet</name>
		<pose>Unspecified</pose>
		<truncated>0</truncated>
		<difficult>0</difficult>
		<bndbox>
			<xmin>2114</xmin>
			<ymin>1963</ymin>
			<xmax>2137</xmax>
			<ymax>1978</ymax>
		</bndbox>
	</object>
	<object>
		<name>helmet</name>
		<pose>Unspecified</pose>
		<truncated>0</truncated>
		<difficult>0</difficult>
		<bndbox>
			<xmin>2131</xmin>
			<ymin>1982</ymin>
			<xmax>2150</xmax>
			<ymax>2009</ymax>
		</bndbox>
	</object>
	<object>
		<name>helmet</name>
		<pose>Unspecified</pose>
		<truncated>0</truncated>
		<difficult>0</difficult>
		<bndbox>
			<xmin>2924</xmin>
			<ymin>1186</ymin>
			<xmax>2935</xmax>
			<ymax>1199</ymax>
		</bndbox>
	</object>
	<object>
		<name>vest</name>
		<pose>Unspecified</pose>
		<truncated>0</truncated>
		<difficult>0</difficult>
		<bndbox>
			<xmin>2925</xmin>
			<ymin>1196</ymin>
			<xmax>2947</xmax>
			<ymax>1217</ymax>
		</bndbox>
	</object>
	</annotation>