<annotation>
	<folder>photo</folder>
	<filename>hptm8300.jpg</filename>
	<path>C:\Users\CZT\Desktop\data\photo\hptm8300.jpg</path>
	<source>
		<database>Unknown</database>
	</source>
	<size>
		<width>1920</width>
		<height>1080</height>
		<depth>3</depth>
	</size>
	<segmented>0</segmented>
	<object>
		<name>person</name>
		<pose>Unspecified</pose>
		<truncated>0</truncated>
		<difficult>0</difficult>
		<bndbox>
			<xmin>434</xmin>
			<ymin>623</ymin>
			<xmax>538</xmax>
			<ymax>878</ymax>
		</bndbox>
	</object>
	<object>
		<name>person</name>
		<pose>Unspecified</pose>
		<truncated>0</truncated>
		<difficult>0</difficult>
		<bndbox>
			<xmin>692</xmin>
			<ymin>537</ymin>
			<xmax>785</xmax>
			<ymax>767</ymax>
		</bndbox>
	</object>
	<object>
		<name>helmet</name>
		<pose>Unspecified</pose>
		<truncated>0</truncated>
		<difficult>0</difficult>
		<bndbox>
			<xmin>708</xmin>
			<ymin>534</ymin>
			<xmax>760</xmax>
			<ymax>574</ymax>
		</bndbox>
	</object>
	<object>
		<name>helmet</name>
		<pose>Unspecified</pose>
		<truncated>0</truncated>
		<difficult>0</difficult>
		<bndbox>
			<xmin>463</xmin>
			<ymin>622</ymin>
			<xmax>503</xmax>
			<ymax>652</ymax>
		</bndbox>
	</object>
	<object>
		<name>vest</name>
		<pose>Unspecified</pose>
		<truncated>0</truncated>
		<difficult>0</difficult>
		<bndbox>
			<xmin>706</xmin>
			<ymin>577</ymin>
			<xmax>766</xmax>
			<ymax>689</ymax>
		</bndbox>
	</object>
	<object>
		<name>vest</name>
		<pose>Unspecified</pose>
		<truncated>0</truncated>
		<difficult>0</difficult>
		<bndbox>
			<xmin>447</xmin>
			<ymin>660</ymin>
			<xmax>531</xmax>
			<ymax>758</ymax>
		</bndbox>
	</object>
	</annotation>