<annotation>
	<folder></folder>
	<filename>image_from_china-288-_jpg.rf.c71a6d3354f42d175b7e78f3bf866290.jpg</filename>
	<path>image_from_china-288-_jpg.rf.c71a6d3354f42d175b7e78f3bf866290.jpg</path>
	<source>
		<database>roboflow.ai</database>
	</source>
	<size>
		<width>416</width>
		<height>416</height>
		<depth>3</depth>
	</size>
	<segmented>0</segmented>
	<object>
		<name>person</name>
		<pose>Unspecified</pose>
		<truncated>0</truncated>
		<difficult>0</difficult>
		<occluded>0</occluded>
		<bndbox>
			<xmin>1</xmin>
			<xmax>92</xmax>
			<ymin>144</ymin>
			<ymax>318</ymax>
		</bndbox>
	</object>
	<object>
		<name>person</name>
		<pose>Unspecified</pose>
		<truncated>0</truncated>
		<difficult>0</difficult>
		<occluded>0</occluded>
		<bndbox>
			<xmin>382</xmin>
			<xmax>407</xmax>
			<ymin>172</ymin>
			<ymax>210</ymax>
		</bndbox>
	</object>
	<object>
		<name>helmet</name>
		<pose>Unspecified</pose>
		<truncated>0</truncated>
		<difficult>0</difficult>
		<occluded>0</occluded>
		<bndbox>
			<xmin>60</xmin>
			<xmax>91</xmax>
			<ymin>144</ymin>
			<ymax>183</ymax>
		</bndbox>
	</object>
</annotation>
