<annotation>
	<folder>part1</folder>
	<filename>hd1987.jpg</filename>
	<path>C:\z\data\photo\part1\hd1987.jpg</path>
	<source>
		<database>Unknown</database>
	</source>
	<size>
		<width>1920</width>
		<height>1080</height>
		<depth>3</depth>
	</size>
	<segmented>0</segmented>
	<object>
		<name>person</name>
		<pose>Unspecified</pose>
		<truncated>1</truncated>
		<difficult>0</difficult>
		<bndbox>
			<xmin>124</xmin>
			<ymin>591</ymin>
			<xmax>349</xmax>
			<ymax>1080</ymax>
		</bndbox>
	</object>
	<object>
		<name>person</name>
		<pose>Unspecified</pose>
		<truncated>0</truncated>
		<difficult>0</difficult>
		<bndbox>
			<xmin>556</xmin>
			<ymin>582</ymin>
			<xmax>667</xmax>
			<ymax>928</ymax>
		</bndbox>
	</object>
	<object>
		<name>person</name>
		<pose>Unspecified</pose>
		<truncated>0</truncated>
		<difficult>0</difficult>
		<bndbox>
			<xmin>659</xmin>
			<ymin>595</ymin>
			<xmax>719</xmax>
			<ymax>887</ymax>
		</bndbox>
	</object>
	<object>
		<name>person</name>
		<pose>Unspecified</pose>
		<truncated>0</truncated>
		<difficult>0</difficult>
		<bndbox>
			<xmin>785</xmin>
			<ymin>587</ymin>
			<xmax>908</xmax>
			<ymax>965</ymax>
		</bndbox>
	</object>
	<object>
		<name>person</name>
		<pose>Unspecified</pose>
		<truncated>0</truncated>
		<difficult>0</difficult>
		<bndbox>
			<xmin>969</xmin>
			<ymin>605</ymin>
			<xmax>1050</xmax>
			<ymax>894</ymax>
		</bndbox>
	</object>
	<object>
		<name>person</name>
		<pose>Unspecified</pose>
		<truncated>0</truncated>
		<difficult>0</difficult>
		<bndbox>
			<xmin>1268</xmin>
			<ymin>605</ymin>
			<xmax>1394</xmax>
			<ymax>909</ymax>
		</bndbox>
	</object>
	<object>
		<name>helmet</name>
		<pose>Unspecified</pose>
		<truncated>0</truncated>
		<difficult>0</difficult>
		<bndbox>
			<xmin>173</xmin>
			<ymin>592</ymin>
			<xmax>282</xmax>
			<ymax>658</ymax>
		</bndbox>
	</object>
	<object>
		<name>helmet</name>
		<pose>Unspecified</pose>
		<truncated>0</truncated>
		<difficult>0</difficult>
		<bndbox>
			<xmin>608</xmin>
			<ymin>584</ymin>
			<xmax>654</xmax>
			<ymax>623</ymax>
		</bndbox>
	</object>
	<object>
		<name>helmet</name>
		<pose>Unspecified</pose>
		<truncated>0</truncated>
		<difficult>0</difficult>
		<bndbox>
			<xmin>675</xmin>
			<ymin>597</ymin>
			<xmax>715</xmax>
			<ymax>624</ymax>
		</bndbox>
	</object>
	<object>
		<name>helmet</name>
		<pose>Unspecified</pose>
		<truncated>0</truncated>
		<difficult>0</difficult>
		<bndbox>
			<xmin>821</xmin>
			<ymin>585</ymin>
			<xmax>870</xmax>
			<ymax>622</ymax>
		</bndbox>
	</object>
	<object>
		<name>helmet</name>
		<pose>Unspecified</pose>
		<truncated>0</truncated>
		<difficult>0</difficult>
		<bndbox>
			<xmin>983</xmin>
			<ymin>606</ymin>
			<xmax>1027</xmax>
			<ymax>642</ymax>
		</bndbox>
	</object>
	<object>
		<name>helmet</name>
		<pose>Unspecified</pose>
		<truncated>0</truncated>
		<difficult>0</difficult>
		<bndbox>
			<xmin>1305</xmin>
			<ymin>604</ymin>
			<xmax>1354</xmax>
			<ymax>642</ymax>
		</bndbox>
	</object>
	<object>
		<name>vest</name>
		<pose>Unspecified</pose>
		<truncated>0</truncated>
		<difficult>0</difficult>
		<bndbox>
			<xmin>127</xmin>
			<ymin>706</ymin>
			<xmax>298</xmax>
			<ymax>958</ymax>
		</bndbox>
	</object>
	<object>
		<name>vest</name>
		<pose>Unspecified</pose>
		<truncated>0</truncated>
		<difficult>0</difficult>
		<bndbox>
			<xmin>656</xmin>
			<ymin>645</ymin>
			<xmax>717</xmax>
			<ymax>757</ymax>
		</bndbox>
	</object>
	<object>
		<name>vest</name>
		<pose>Unspecified</pose>
		<truncated>0</truncated>
		<difficult>0</difficult>
		<bndbox>
			<xmin>792</xmin>
			<ymin>641</ymin>
			<xmax>882</xmax>
			<ymax>781</ymax>
		</bndbox>
	</object>
	<object>
		<name>vest</name>
		<pose>Unspecified</pose>
		<truncated>0</truncated>
		<difficult>0</difficult>
		<bndbox>
			<xmin>971</xmin>
			<ymin>661</ymin>
			<xmax>1031</xmax>
			<ymax>769</ymax>
		</bndbox>
	</object>
	<object>
		<name>vest</name>
		<pose>Unspecified</pose>
		<truncated>0</truncated>
		<difficult>0</difficult>
		<bndbox>
			<xmin>1311</xmin>
			<ymin>653</ymin>
			<xmax>1394</xmax>
			<ymax>768</ymax>
		</bndbox>
	</object>
	</annotation>