<annotation>
	<folder>photo</folder>
	<filename>hptm1544.jpg</filename>
	<path>F:\gongzuofang\data\photo\hptm1544.jpg</path>
	<source>
		<database>Unknown</database>
	</source>
	<size>
		<width>1920</width>
		<height>1080</height>
		<depth>3</depth>
	</size>
	<segmented>0</segmented>
	<object>
		<name>rebar</name>
		<pose>Unspecified</pose>
		<truncated>0</truncated>
		<difficult>0</difficult>
		<bndbox>
			<xmin>1493</xmin>
			<ymin>49</ymin>
			<xmax>1746</xmax>
			<ymax>109</ymax>
		</bndbox>
	</object>
	<object>
		<name>cutter</name>
		<pose>Unspecified</pose>
		<truncated>0</truncated>
		<difficult>0</difficult>
		<bndbox>
			<xmin>1511</xmin>
			<ymin>71</ymin>
			<xmax>1568</xmax>
			<ymax>128</ymax>
		</bndbox>
	</object>
</annotation>
