<?xml version='1.0' encoding='utf-8'?>
<annotation>
	<folder>photo</folder>
	<filename>hptm1419.jpg</filename>
	<path>F:\gongzuofang\data\photo\hptm1419.jpg</path>
	<source>
		<database>Unknown</database>
	</source>
	<size>
		<width>1920</width>
		<height>1080</height>
		<depth>3</depth>
	</size>
	<segmented>0</segmented>
	<object>
		<name>person</name>
		<pose>Unspecified</pose>
		<truncated>0</truncated>
		<difficult>0</difficult>
		<bndbox>
			<xmin>1338</xmin>
			<ymin>89</ymin>
			<xmax>1395</xmax>
			<ymax>220</ymax>
		</bndbox>
	</object>
	<object>
		<name>rebar</name>
		<pose>Unspecified</pose>
		<truncated>1</truncated>
		<difficult>0</difficult>
		<bndbox>
			<xmin>1</xmin>
			<ymin>446</ymin>
			<xmax>645</xmax>
			<ymax>814</ymax>
		</bndbox>
	</object>
	<object>
		<name>rebar</name>
		<pose>Unspecified</pose>
		<truncated>1</truncated>
		<difficult>0</difficult>
		<bndbox>
			<xmin>1</xmin>
			<ymin>224</ymin>
			<xmax>391</xmax>
			<ymax>484</ymax>
		</bndbox>
	</object>
	<object>
		<name>hopper</name>
		<pose>Unspecified</pose>
		<truncated>0</truncated>
		<difficult>0</difficult>
		<bndbox>
			<xmin>1198</xmin>
			<ymin>207</ymin>
			<xmax>1497</xmax>
			<ymax>373</ymax>
		</bndbox>
	</object>
	<object>
		<name>fence</name>
		<pose>Unspecified</pose>
		<truncated>1</truncated>
		<difficult>0</difficult>
		<bndbox>
			<xmin>1400</xmin>
			<ymin>121</ymin>
			<xmax>1920</xmax>
			<ymax>537</ymax>
		</bndbox>
	</object>
	<object>
		<name>vest</name>
		<pose>Unspecified</pose>
		<truncated>0</truncated>
		<difficult>0</difficult>
		<bndbox>
			<xmin>1345</xmin>
			<ymin>130</ymin>
			<xmax>1384</xmax>
			<ymax>195</ymax>
		</bndbox>
	</object>
	<object>
		<name>helmet</name>
		<pose>Unspecified</pose>
		<truncated>0</truncated>
		<difficult>0</difficult>
		<bndbox>
			<xmin>1353</xmin>
			<ymin>91</ymin>
			<xmax>1385</xmax>
			<ymax>110</ymax>
		</bndbox>
	</object>
</annotation>