<annotation>
	<folder>photo</folder>
	<filename>zl170.jpg</filename>
	<path>E:\dododo\data\photo\zl170.jpg</path>
	<source>
		<database>Unknown</database>
	</source>
	<size>
		<width>4032</width>
		<height>3024</height>
		<depth>3</depth>
	</size>
	<segmented>0</segmented>
	<object>
		<name>hopper</name>
		<pose>Unspecified</pose>
		<truncated>0</truncated>
		<difficult>0</difficult>
		<bndbox>
			<xmin>659</xmin>
			<ymin>763</ymin>
			<xmax>3020</xmax>
			<ymax>2105</ymax>
		</bndbox>
	</object>
	<object>
		<name>handcart</name>
		<pose>Unspecified</pose>
		<truncated>0</truncated>
		<difficult>0</difficult>
		<bndbox>
			<xmin>1220</xmin>
			<ymin>469</ymin>
			<xmax>2191</xmax>
			<ymax>969</ymax>
		</bndbox>
	</object>
	<object>
		<name>scaffold</name>
		<pose>Unspecified</pose>
		<truncated>0</truncated>
		<difficult>0</difficult>
		<bndbox>
			<xmin>2744</xmin>
			<ymin>183</ymin>
			<xmax>3081</xmax>
			<ymax>409</ymax>
		</bndbox>
	</object>
</annotation>
