<annotation>
	<folder>photo</folder>
	<filename>hook1412.jpg</filename>
	<path>C:\z\data\photo\part2\photo\hook1412.jpg</path>
	<source>
		<database>Unknown</database>
	</source>
	<size>
		<width>1920</width>
		<height>1080</height>
		<depth>3</depth>
	</size>
	<segmented>0</segmented>
	<object>
		<name>hook</name>
		<pose>Unspecified</pose>
		<truncated>0</truncated>
		<difficult>0</difficult>
		<bndbox>
			<xmin>862</xmin>
			<ymin>372</ymin>
			<xmax>919</xmax>
			<ymax>524</ymax>
		</bndbox>
	</object>
	<object>
		<name>person</name>
		<pose>Unspecified</pose>
		<truncated>0</truncated>
		<difficult>0</difficult>
		<bndbox>
			<xmin>845</xmin>
			<ymin>344</ymin>
			<xmax>931</xmax>
			<ymax>391</ymax>
		</bndbox>
	</object>
	<object>
		<name>person</name>
		<pose>Unspecified</pose>
		<truncated>0</truncated>
		<difficult>0</difficult>
		<bndbox>
			<xmin>1040</xmin>
			<ymin>745</ymin>
			<xmax>1110</xmax>
			<ymax>808</ymax>
		</bndbox>
	</object>
	<object>
		<name>helmet</name>
		<pose>Unspecified</pose>
		<truncated>0</truncated>
		<difficult>0</difficult>
		<bndbox>
			<xmin>905</xmin>
			<ymin>344</ymin>
			<xmax>929</xmax>
			<ymax>370</ymax>
		</bndbox>
	</object>
	<object>
		<name>helmet</name>
		<pose>Unspecified</pose>
		<truncated>0</truncated>
		<difficult>0</difficult>
		<bndbox>
			<xmin>1046</xmin>
			<ymin>771</ymin>
			<xmax>1070</xmax>
			<ymax>793</ymax>
		</bndbox>
	</object>
	<object>
		<name>person</name>
		<pose>Unspecified</pose>
		<truncated>1</truncated>
		<difficult>0</difficult>
		<bndbox>
			<xmin>1</xmin>
			<ymin>188</ymin>
			<xmax>43</xmax>
			<ymax>249</ymax>
		</bndbox>
	</object>
	<object>
		<name>rebar</name>
		<pose>Unspecified</pose>
		<truncated>0</truncated>
		<difficult>0</difficult>
		<bndbox>
			<xmin>438</xmin>
			<ymin>530</ymin>
			<xmax>614</xmax>
			<ymax>842</ymax>
		</bndbox>
	</object>
	<object>
		<name>rebar</name>
		<pose>Unspecified</pose>
		<truncated>0</truncated>
		<difficult>0</difficult>
		<bndbox>
			<xmin>534</xmin>
			<ymin>190</ymin>
			<xmax>1164</xmax>
			<ymax>535</ymax>
		</bndbox>
	</object>
	<object>
		<name>scaffold</name>
		<pose>Unspecified</pose>
		<truncated>0</truncated>
		<difficult>0</difficult>
		<bndbox>
			<xmin>912</xmin>
			<ymin>189</ymin>
			<xmax>1082</xmax>
			<ymax>392</ymax>
		</bndbox>
	</object>
</annotation>
