<annotation>
	<folder>photo</folder>
	<filename>hook1785.jpg</filename>
	<path>C:\z\data\photo\part2\photo\hook1785.jpg</path>
	<source>
		<database>Unknown</database>
	</source>
	<size>
		<width>1920</width>
		<height>1080</height>
		<depth>3</depth>
	</size>
	<segmented>0</segmented>
	<object>
		<name>hook</name>
		<pose>Unspecified</pose>
		<truncated>0</truncated>
		<difficult>0</difficult>
		<bndbox>
			<xmin>858</xmin>
			<ymin>374</ymin>
			<xmax>882</xmax>
			<ymax>490</ymax>
		</bndbox>
	</object>
	<object>
		<name>rebar</name>
		<pose>Unspecified</pose>
		<truncated>0</truncated>
		<difficult>0</difficult>
		<bndbox>
			<xmin>582</xmin>
			<ymin>387</ymin>
			<xmax>1146</xmax>
			<ymax>489</ymax>
		</bndbox>
	</object>
	<object>
		<name>rebar</name>
		<pose>Unspecified</pose>
		<truncated>0</truncated>
		<difficult>0</difficult>
		<bndbox>
			<xmin>1393</xmin>
			<ymin>527</ymin>
			<xmax>1634</xmax>
			<ymax>616</ymax>
		</bndbox>
	</object>
	<object>
		<name>rebar</name>
		<pose>Unspecified</pose>
		<truncated>0</truncated>
		<difficult>0</difficult>
		<bndbox>
			<xmin>1404</xmin>
			<ymin>569</ymin>
			<xmax>1644</xmax>
			<ymax>663</ymax>
		</bndbox>
	</object>
	<object>
		<name>rebar</name>
		<pose>Unspecified</pose>
		<truncated>0</truncated>
		<difficult>0</difficult>
		<bndbox>
			<xmin>1468</xmin>
			<ymin>512</ymin>
			<xmax>1592</xmax>
			<ymax>693</ymax>
		</bndbox>
	</object>
	<object>
		<name>rebar</name>
		<pose>Unspecified</pose>
		<truncated>0</truncated>
		<difficult>0</difficult>
		<bndbox>
			<xmin>1515</xmin>
			<ymin>462</ymin>
			<xmax>1617</xmax>
			<ymax>692</ymax>
		</bndbox>
	</object>
	<object>
		<name>wood</name>
		<pose>Unspecified</pose>
		<truncated>0</truncated>
		<difficult>0</difficult>
		<bndbox>
			<xmin>1348</xmin>
			<ymin>572</ymin>
			<xmax>1390</xmax>
			<ymax>621</ymax>
		</bndbox>
	</object>
</annotation>
