<?xml version='1.0' encoding='utf-8'?>
<annotation>
	<folder>photo</folder>
	<filename>hptm5892.jpg</filename>
	<path>C:\Users\dell\Desktop\gzf\lable(25)\photo\hptm5892.jpg</path>
	<source>
		<database>Unknown</database>
	</source>
	<size>
		<width>1920</width>
		<height>1080</height>
		<depth>3</depth>
	</size>
	<segmented>0</segmented>
	<object>
		<name>person</name>
		<pose>Unspecified</pose>
		<truncated>0</truncated>
		<difficult>0</difficult>
		<bndbox>
			<xmin>936</xmin>
			<ymin>310</ymin>
			<xmax>1008</xmax>
			<ymax>474</ymax>
		</bndbox>
	</object>
	<object>
		<name>person</name>
		<pose>Unspecified</pose>
		<truncated>1</truncated>
		<difficult>0</difficult>
		<bndbox>
			<xmin>452</xmin>
			<ymin>860</ymin>
			<xmax>542</xmax>
			<ymax>1080</ymax>
		</bndbox>
	</object>
	<object>
		<name>person</name>
		<pose>Unspecified</pose>
		<truncated>0</truncated>
		<difficult>0</difficult>
		<bndbox>
			<xmin>194</xmin>
			<ymin>565</ymin>
			<xmax>267</xmax>
			<ymax>756</ymax>
		</bndbox>
	</object>
	<object>
		<name>helmet</name>
		<pose>Unspecified</pose>
		<truncated>0</truncated>
		<difficult>0</difficult>
		<bndbox>
			<xmin>476</xmin>
			<ymin>859</ymin>
			<xmax>515</xmax>
			<ymax>889</ymax>
		</bndbox>
	</object>
	<object>
		<name>vest</name>
		<pose>Unspecified</pose>
		<truncated>0</truncated>
		<difficult>0</difficult>
		<bndbox>
			<xmin>959</xmin>
			<ymin>343</ymin>
			<xmax>1004</xmax>
			<ymax>406</ymax>
		</bndbox>
	</object>
	<object>
		<name>helmet</name>
		<pose>Unspecified</pose>
		<truncated>0</truncated>
		<difficult>0</difficult>
		<bndbox>
			<xmin>942</xmin>
			<ymin>310</ymin>
			<xmax>975</xmax>
			<ymax>337</ymax>
		</bndbox>
	</object>
	<object>
		<name>wood</name>
		<pose>Unspecified</pose>
		<truncated>0</truncated>
		<difficult>0</difficult>
		<bndbox>
			<xmin>436</xmin>
			<ymin>216</ymin>
			<xmax>705</xmax>
			<ymax>338</ymax>
		</bndbox>
	</object>
	<object>
		<name>wood</name>
		<pose>Unspecified</pose>
		<truncated>0</truncated>
		<difficult>0</difficult>
		<bndbox>
			<xmin>8</xmin>
			<ymin>733</ymin>
			<xmax>283</xmax>
			<ymax>833</ymax>
		</bndbox>
	</object>
	<object>
		<name>wood</name>
		<pose>Unspecified</pose>
		<truncated>1</truncated>
		<difficult>0</difficult>
		<bndbox>
			<xmin>1</xmin>
			<ymin>458</ymin>
			<xmax>249</xmax>
			<ymax>592</ymax>
		</bndbox>
	</object>
	<object>
		<name>wood</name>
		<pose>Unspecified</pose>
		<truncated>0</truncated>
		<difficult>0</difficult>
		<bndbox>
			<xmin>415</xmin>
			<ymin>520</ymin>
			<xmax>581</xmax>
			<ymax>668</ymax>
		</bndbox>
	</object>
	<object>
		<name>rebar</name>
		<pose>Unspecified</pose>
		<truncated>0</truncated>
		<difficult>0</difficult>
		<bndbox>
			<xmin>817</xmin>
			<ymin>389</ymin>
			<xmax>1350</xmax>
			<ymax>541</ymax>
		</bndbox>
	</object>
</annotation>