<annotation>
	<folder>photo</folder>
	<filename>hpdr2807.jpg</filename>
	<path>C:\Users\15451\Desktop\数据集构建\data\photo\hpdr2807.jpg</path>
	<source>
		<database>Unknown</database>
	</source>
	<size>
		<width>1920</width>
		<height>1080</height>
		<depth>3</depth>
	</size>
	<segmented>0</segmented>
	<object>
		<name>scaffold</name>
		<pose>Unspecified</pose>
		<truncated>0</truncated>
		<difficult>0</difficult>
		<bndbox>
			<xmin>1070</xmin>
			<ymin>383</ymin>
			<xmax>1538</xmax>
			<ymax>507</ymax>
		</bndbox>
	</object>
	<object>
		<name>scaffold</name>
		<pose>Unspecified</pose>
		<truncated>0</truncated>
		<difficult>0</difficult>
		<bndbox>
			<xmin>1052</xmin>
			<ymin>500</ymin>
			<xmax>1663</xmax>
			<ymax>656</ymax>
		</bndbox>
	</object>
	<object>
		<name>scaffold</name>
		<pose>Unspecified</pose>
		<truncated>1</truncated>
		<difficult>0</difficult>
		<bndbox>
			<xmin>1600</xmin>
			<ymin>433</ymin>
			<xmax>1920</xmax>
			<ymax>597</ymax>
		</bndbox>
	</object>
	<object>
		<name>scaffold</name>
		<pose>Unspecified</pose>
		<truncated>0</truncated>
		<difficult>0</difficult>
		<bndbox>
			<xmin>117</xmin>
			<ymin>516</ymin>
			<xmax>273</xmax>
			<ymax>633</ymax>
		</bndbox>
	</object>
	<object>
		<name>scaffold</name>
		<pose>Unspecified</pose>
		<truncated>0</truncated>
		<difficult>0</difficult>
		<bndbox>
			<xmin>274</xmin>
			<ymin>493</ymin>
			<xmax>510</xmax>
			<ymax>593</ymax>
		</bndbox>
	</object>
	<object>
		<name>scaffold</name>
		<pose>Unspecified</pose>
		<truncated>0</truncated>
		<difficult>0</difficult>
		<bndbox>
			<xmin>226</xmin>
			<ymin>581</ymin>
			<xmax>385</xmax>
			<ymax>716</ymax>
		</bndbox>
	</object>
	<object>
		<name>scaffold</name>
		<pose>Unspecified</pose>
		<truncated>0</truncated>
		<difficult>0</difficult>
		<bndbox>
			<xmin>373</xmin>
			<ymin>568</ymin>
			<xmax>515</xmax>
			<ymax>670</ymax>
		</bndbox>
	</object>
	<object>
		<name>scaffold</name>
		<pose>Unspecified</pose>
		<truncated>0</truncated>
		<difficult>0</difficult>
		<bndbox>
			<xmin>681</xmin>
			<ymin>473</ymin>
			<xmax>825</xmax>
			<ymax>517</ymax>
		</bndbox>
	</object>
	<object>
		<name>hopper</name>
		<pose>Unspecified</pose>
		<truncated>0</truncated>
		<difficult>0</difficult>
		<bndbox>
			<xmin>555</xmin>
			<ymin>565</ymin>
			<xmax>819</xmax>
			<ymax>696</ymax>
		</bndbox>
	</object>
	<object>
		<name>fence</name>
		<pose>Unspecified</pose>
		<truncated>1</truncated>
		<difficult>0</difficult>
		<bndbox>
			<xmin>1</xmin>
			<ymin>596</ymin>
			<xmax>141</xmax>
			<ymax>783</ymax>
		</bndbox>
	</object>
</annotation>
