<?xml version='1.0' encoding='utf-8'?>
<annotation>
	<folder>photo</folder>
	<filename>hptm6590.jpg</filename>
	<path>C:\Users\Ina Aono\Desktop\wdyj\data\photo\hptm6590.jpg</path>
	<source>
		<database>Unknown</database>
	</source>
	<size>
		<width>1920</width>
		<height>1080</height>
		<depth>3</depth>
	</size>
	<segmented>0</segmented>
	<object>
		<name>person</name>
		<pose>Unspecified</pose>
		<truncated>0</truncated>
		<difficult>0</difficult>
		<bndbox>
			<xmin>1467</xmin>
			<ymin>679</ymin>
			<xmax>1504</xmax>
			<ymax>816</ymax>
		</bndbox>
	</object>
	<object>
		<name>helmet</name>
		<pose>Unspecified</pose>
		<truncated>0</truncated>
		<difficult>0</difficult>
		<bndbox>
			<xmin>1475</xmin>
			<ymin>680</ymin>
			<xmax>1492</xmax>
			<ymax>699</ymax>
		</bndbox>
	</object>
	<object>
		<name>person</name>
		<pose>Unspecified</pose>
		<truncated>0</truncated>
		<difficult>0</difficult>
		<bndbox>
			<xmin>1651</xmin>
			<ymin>689</ymin>
			<xmax>1673</xmax>
			<ymax>790</ymax>
		</bndbox>
	</object>
	<object>
		<name>vest</name>
		<pose>Unspecified</pose>
		<truncated>0</truncated>
		<difficult>0</difficult>
		<bndbox>
			<xmin>1473</xmin>
			<ymin>711</ymin>
			<xmax>1498</xmax>
			<ymax>751</ymax>
		</bndbox>
	</object>
</annotation>