<?xml version='1.0' encoding='utf-8'?>
<annotation>
	<folder>photo</folder>
	<filename>hptm854.jpg</filename>
	<path>C:\data\photo\hptm854.jpg</path>
	<source>
		<database>Unknown</database>
	</source>
	<size>
		<width>1920</width>
		<height>1080</height>
		<depth>3</depth>
	</size>
	<segmented>0</segmented>
	<object>
		<name>wood</name>
		<pose>Unspecified</pose>
		<truncated>0</truncated>
		<difficult>0</difficult>
		<bndbox>
			<xmin>354</xmin>
			<ymin>355</ymin>
			<xmax>841</xmax>
			<ymax>464</ymax>
		</bndbox>
	</object>
	<object>
		<name>brick</name>
		<pose>Unspecified</pose>
		<truncated>0</truncated>
		<difficult>0</difficult>
		<bndbox>
			<xmin>182</xmin>
			<ymin>322</ymin>
			<xmax>454</xmax>
			<ymax>431</ymax>
		</bndbox>
	</object>
	<object>
		<name>slogan</name>
		<pose>Unspecified</pose>
		<truncated>0</truncated>
		<difficult>0</difficult>
		<bndbox>
			<xmin>25</xmin>
			<ymin>183</ymin>
			<xmax>515</xmax>
			<ymax>249</ymax>
		</bndbox>
	</object>
	<object>
		<name>slogan</name>
		<pose>Unspecified</pose>
		<truncated>0</truncated>
		<difficult>0</difficult>
		<bndbox>
			<xmin>956</xmin>
			<ymin>155</ymin>
			<xmax>1160</xmax>
			<ymax>214</ymax>
		</bndbox>
	</object>
	<object>
		<name>slogan</name>
		<pose>Unspecified</pose>
		<truncated>0</truncated>
		<difficult>0</difficult>
		<bndbox>
			<xmin>1397</xmin>
			<ymin>47</ymin>
			<xmax>1888</xmax>
			<ymax>142</ymax>
		</bndbox>
	</object>
	<object>
		<name>slogan</name>
		<pose>Unspecified</pose>
		<truncated>0</truncated>
		<difficult>0</difficult>
		<bndbox>
			<xmin>1260</xmin>
			<ymin>199</ymin>
			<xmax>1425</xmax>
			<ymax>246</ymax>
		</bndbox>
	</object>
	<object>
		<name>slogan</name>
		<pose>Unspecified</pose>
		<truncated>0</truncated>
		<difficult>0</difficult>
		<bndbox>
			<xmin>1482</xmin>
			<ymin>203</ymin>
			<xmax>1725</xmax>
			<ymax>257</ymax>
		</bndbox>
	</object>
	<object>
		<name>person</name>
		<pose>Unspecified</pose>
		<truncated>0</truncated>
		<difficult>0</difficult>
		<bndbox>
			<xmin>1456</xmin>
			<ymin>262</ymin>
			<xmax>1530</xmax>
			<ymax>422</ymax>
		</bndbox>
	</object>
	<object>
		<name>vest</name>
		<pose>Unspecified</pose>
		<truncated>0</truncated>
		<difficult>0</difficult>
		<bndbox>
			<xmin>1465</xmin>
			<ymin>294</ymin>
			<xmax>1512</xmax>
			<ymax>351</ymax>
		</bndbox>
	</object>
	<object>
		<name>helmet</name>
		<pose>Unspecified</pose>
		<truncated>0</truncated>
		<difficult>0</difficult>
		<bndbox>
			<xmin>1478</xmin>
			<ymin>268</ymin>
			<xmax>1495</xmax>
			<ymax>277</ymax>
		</bndbox>
	</object>
	<object>
		<name>ebox</name>
		<pose>Unspecified</pose>
		<truncated>0</truncated>
		<difficult>0</difficult>
		<bndbox>
			<xmin>1116</xmin>
			<ymin>274</ymin>
			<xmax>1161</xmax>
			<ymax>333</ymax>
		</bndbox>
	</object>
	<object>
		<name>ebox</name>
		<pose>Unspecified</pose>
		<truncated>0</truncated>
		<difficult>0</difficult>
		<bndbox>
			<xmin>1231</xmin>
			<ymin>289</ymin>
			<xmax>1263</xmax>
			<ymax>331</ymax>
		</bndbox>
	</object>
	<object>
		<name>person</name>
		<pose>Unspecified</pose>
		<truncated>0</truncated>
		<difficult>0</difficult>
		<bndbox>
			<xmin>503</xmin>
			<ymin>275</ymin>
			<xmax>528</xmax>
			<ymax>308</ymax>
		</bndbox>
	</object>
	<object>
		<name>person</name>
		<pose>Unspecified</pose>
		<truncated>0</truncated>
		<difficult>0</difficult>
		<bndbox>
			<xmin>240</xmin>
			<ymin>278</ymin>
			<xmax>265</xmax>
			<ymax>315</ymax>
		</bndbox>
	</object>
	<object>
		<name>helmet</name>
		<pose>Unspecified</pose>
		<truncated>0</truncated>
		<difficult>0</difficult>
		<bndbox>
			<xmin>245</xmin>
			<ymin>279</ymin>
			<xmax>265</xmax>
			<ymax>297</ymax>
		</bndbox>
	</object>
	<object>
		<name>helmet</name>
		<pose>Unspecified</pose>
		<truncated>0</truncated>
		<difficult>0</difficult>
		<bndbox>
			<xmin>509</xmin>
			<ymin>275</ymin>
			<xmax>522</xmax>
			<ymax>286</ymax>
		</bndbox>
	</object>
	<object>
		<name>vest</name>
		<pose>Unspecified</pose>
		<truncated>0</truncated>
		<difficult>0</difficult>
		<bndbox>
			<xmin>511</xmin>
			<ymin>286</ymin>
			<xmax>530</xmax>
			<ymax>306</ymax>
		</bndbox>
	</object>
</annotation>